AlgebraicExpressionParser/__init__.py
AlgebraicExpressionParser/exceptions/Exceptions.py
AlgebraicExpressionParser/exceptions/__init__.py
AlgebraicExpressionParser/expression/Expression.py
AlgebraicExpressionParser/expression/__init__.py
Algebraic_Expression_Parser-0.0.2.dist-info/METADATA
Algebraic_Expression_Parser-0.0.2.dist-info/WHEEL
Algebraic_Expression_Parser-0.0.2.dist-info/top_level.txt
Algebraic_Expression_Parser-0.0.2.dist-info/RECORD
